neo_airpress/__init__.py
neo_airpress/compressor.py
neo_airpress/crypto.py
neo_airpress/pkcs7.py
neo_airpress-2.0.5.dist-info/METADATA
neo_airpress-2.0.5.dist-info/WHEEL
neo_airpress-2.0.5.dist-info/licenses/LICENSE
neo_airpress-2.0.5.dist-info/RECORD
