Metadata-Version: 2.4
Name: neo-airpress
Version: 2.0.5
Summary: A frustration-free compression tool for PKPass archives.
Project-URL: Homepage, https://github.com/jontyms/neo-airpress
Author-email: Jstyles <jstyles@styl.dev>
License-File: LICENSE
Classifier: Operating System :: OS Independent
Classifier: Programming Language :: Python
Classifier: Programming Language :: Python :: 3.10
Classifier: Programming Language :: Python :: 3.11
Classifier: Programming Language :: Python :: 3.12
Classifier: Programming Language :: Python :: 3.13
Requires-Python: >=3.10
Requires-Dist: cryptography>=44.0.0
